pyminify/__init__.py
pyminify/code_gen.py
pyminify/codegen.py
pyminify/file_util.py
pyminify/node_util.py
pyminify/op_util.py
pyminify/rtrip.py
pyminify/source_repr.py
pyminify/string_repr.py
pyminify/tree_walk.py
pyminify-0.0.1.dist-info/LICENSE
pyminify-0.0.1.dist-info/WHEEL
pyminify-0.0.1.dist-info/METADATA
pyminify-0.0.1.dist-info/RECORD
