Metadata-Version: 2.1
Name: pyminify
Version: 0.0.1
Summary: py minifier
Author-email: calcuis <info@calcu.io>
Classifier: License :: OSI Approved :: MIT License
Project-URL: GitHub, https://github.com/calcuis/pyminify
Project-URL: Issues, https://github.com/calcuis/pyminify/issues
